{
  "Ansari Properties": "09920629073",
  "Green Properties Solution": "09867480808",
  "S.R. Real Estate": "08451981125",
  "Sunshine Property Solutions": "09322289098",
  "Vaishnavi Realtor": "09619060340",
  "Sandip Sawant": "09821030841",
  "Shiv Sai Estate Agency": "09820960455",
  "Amar Real Estate": "09833467278",
  "Brahma Realty": "09920201035",
  "Parasrampuria Estate Agency": "09833194772",
  "Prem Realtors and Paying guest accommodation": "09870021788",
  "DHANLAXMI PROPRTY CONSULTANT": "09320594917",
  "SAHEJRAO REALTORS": "07045906702",
  "Realty Solutions": "09930078101",
  "M/s. Perfect Properties and Consultancy": "08693033369",
  "SiddhiVinayak Estate Agency": "09820020383",
  "Patel properties & Consultancy": "09867367126",
  "DB Realty Ltd.": "18001021999",
  "GRD REALTY PRIVATE LIMITED": "09821313139",
  "Pragati Properties": "09167602153",
  "Jaipuria Estate Agency": "09769503403",
  "Laxmi Estate Agency": "09920686066",
  "Real Estate In Mumbai": "09820166539",
  "Property Junction International": "07701835412",
  "Star Homes India": "02242649911",
  "Balaji Estate Agency": "09869281024",
  "Om Housing Agency": "09820079864",
  "Anil Estate Agency- Commercial Office Space/Industrial Gala For Sale In Goregaon-Ready Possession Flats For Sale In Goregaon": "09820184722",
  "Suyash Estate Consultancy - | Rent & sale of property |": "09167335859",
  "Vibrant Group": "09769097575",
  "HDFC ERGO Insurance Agent: Amitabh Mustakim Ansari": "09167990824",
  "Suvarna Estate Agency": "07710978871",
  "Trending Properties": "09513247824",
  "SAMRAT ESTATE AGENCY": "09867603223",
  "Shree Balaji Housing Agency": "07506118622",
  "PROPERTY SEEDS": "08828161678",
  "Marck Realty": "09987396594",
  "BVCK REALTY LLP": "09820141570",
  "The GoodBrokers": "07738575445",
  "A.N Properties": "09664646047",
  "Vijay Real State": "09773051876",
  "Shiv Shakti Estate Agency": "09820325375",
  "Sunrise properties Goregaon East Mumbai": "09372668189",
  "Ashish Bandodkar real estate consultant": "07039447088",
  "Shreenath Estate Agency (Mukund Batavia)": "02228232915",
  "Bhavya Bhairav Real Estate": "09867980920",
  "S.P.Realtor's": "02228721936",
  "APH Enterprises": "08080753902",
  "Prime Property Dealers": "09821727288",
  "ATLANTA ESTATE AGENCY": "09323900036",
  "National Estate Consultant": "08898813726",
  "Krishna Group": "09022980128",
  "Gajantlakshmi Estate Agency": "09320787393",
  "Sushant Property INDIA": "09870342600",
  "SHUBHASWI REALTORS": "09987207272",
  "Veera Estate Consultant": "09819793658",
  "S K Estate Agency": "09821388331",
  "Murugan Real Estate": "09892685194",
  "Wageshwari Developers": "02228495557",
  "Just Deal Properties - Best real estate agent/best property dealers/Agent In Mumbai": "09930303044",
  "Sai Home Property": "09987151344",
  "Shree Sai Real Estate": "09004194130",
  "My Houss": "09967716589",
  "Sunil Estate Agency | Property Dealer | Rent House | PG service | Home loan": "09920537809",
  "7 Sky Properties": "09004997297",
  "Maa Real estate consultant": "09821414696",
  "Interspace Realtors": "09920714733",
  "Dhruv Estate Agency": "09920239870",
  "Mikki's Real Estate": "09323127788",
  "GAYATRI PROPERTY AND ENTERPRISES": "09820856433",
  "Rj property": "09820372678",
  "OM MANGALAM PROPERTIES": "08850543332",
  "Homesync Real Estate Advisory": "02228749966",
  "Parth Properties": "09167404522",
  "Popular Estate Consultancy": "08898023131",
  "MUMMY'S PROPERTY CONSULTANT": "08369964278",
  "Citizen Associates": "09869241697",
  "Omkar Estate Agency": "09820365755",
  "Goyal Properties": "02228413712",
  "True Space Advisory, Rachit Vora- Top And Best Real Estate Agents/ Brokers in Mumbai": "07303030455",
  "Sharma Realtor": "02240101516",
  "YES2BROKERS": "09867775577",
  "Firstbrick Properties & Finance": "02226863446",
  "J Vinay Realtors": "09833315007",
  "Vijay Estate": "02229258238",
  "Ashiyana Estate Agency ,": "08108365089",
  "Shree Balaji Property & Consultant": "08976330475",
  "Property Shuffle LLP": "07738404969",
  "Mehra Estates": "09594017862",
  "Gupta Housing Estate Agent": "09819479664",
  "RIDDHI-SIDDHI PROPERTY POWAI CHANDIVALI Estate Agents Real Estate Broker Property Agent Property Dealers | Consultant": "09867029445",
  "Dhruv Housing": "09321901515",
  "Shree Real Estate Agents": "09821004399",
  "Bani Realty": "09930857365",
  "Rajesh Real Estate Agency": "08082749950",
  "jagara realty": "09969880387",
  "Rajasthan Estate Realtors": "09819515032",
  "SPY Realtors - Estate Agents in Powai | Real Estate Broker | Property Agent | Kanakia Silicon Valley": "09224341412",
  "Raj Realtors": "07666645866",
  "Uday Co-Operative Housing Society LTD, Anushree Chirmule": "09869016832",
  "Vijay Estate Sales & Purchase": "09619739024",
  "Shree Ganesh Estate Agency": "02228786942",
  "S.S. Estate Consultant": "09820206777",
  "Om Sai Ram Estate Agency": "09833222290",
  "ABHISHEK REAL ESTATE AGENCY Property Consultant": "09920217935",
  "S.S. Properties Agent": "09769873244",
  "SURAJ ESTATE CONSULTANT": "07039299550",
  "Gagangiri Estate Agency": "09969672861",
  "Shankar Real Estate Agent": "09920347184",
  "Shree Siddhi Vinayak Estate Agent": "09820960161",
  "Paresh Estate Agent": "02228782369",
  "Hari Om Estate Agency": "02228429594",
  "Gita Estate Agency": "02238730012",
  "Satnam Property Dealers": "09930939555",
  "Shiv Estate Agency": "09892020209",
  "Prakash Estate Agent": "08424875844",
  "Krishna Estate Agency": "09821548193",
  "Mahaviraay Realtors": "09819250035",
  "Amar Estate Agency": "02228875206"
}