{
  "Shree Siddheshwar Estate Agents": "09220817682",
  "RAJGURU REALTY": "09967535353",
  "Real Estate Consultant - Abbas Ali Arif": "09022328752",
  "The Redstone Group": "03479036296",
  "Sun Insurance Brokers Ltd": "02240232233",
  "Nearesh Real Estate Agent": "09987553684",
  "Mahaveer Riya Estate Consultant": "09867579170",
  "AMISHA REALTORS": "02223840604",
  "Multiplize Investment Services": "02223461013",
  "Kiran Real Estate": "09082241318",
  "Pankaj V Vora and Associates LLP": "02242277777",
  "Dynamic Traders": "04425510060",
  "Basera Real Estate Mumbai": "08879249406",
  "EstateOption.com": "09004672329",
  "Sahiyara Properties Solutions: Estate Agents, Paying Guest For Student in Charni Road Mumbai": "09594652297",
  "Beacon Realty": "02222705157",
  "Kale Estate Consultants": "09820054200",
  "Ajmera Properties - Real Estate Consultant in South Mumbai": "09820251152",
  "Reflex Realty LLP": "02223530606",
  "KAUSHAL INSURANCE": "09987699099",
  "Z Realtors": "09821224454",
  "mohammed property": "09320425152",
  "Eminence Realtors": "09867864611",
  "Rai property contestant": "09975044707",
  "Myoho Realtors": "09892299909",
  "HDFC ERGO Insurance Agent: Ramesh Lakhotia": "09619438308",
  "Bachher Realty": "09167191713",
  "LandLock": "09004476926",
  "Prop Mumbai": "09029786215",
  "Primekey": "09699592732",
  "Jinesh Parmar": "09082601120",
  "Goodplace India": "09820777797",
  "White Housing Realtors": "09820777676",
  "Ananta Landwise Pvt. Ltd.": "02266577400",
  "Premhans Real Estate": "09773984288",
  "Available For Rent": "09324449900",
  "AdiDev Property Consultants": "09076282810",
  "Subham Estates": "09833312345",
  "HDFC ERGO Insurance Agent: Dimple Arvind Jain": "08291251955",
  "HDFC ERGO Insurance Agent: Pinki Kothari": "08879207576",
  "Bhishma Realty Limited": "02222040846",
  "Mangalam Estate Agency": "02223714327",
  "New Creation Realtors": "09833402405",
  "SHRADDHA SABURI ESTATE CONSULTANT": "09820387459",
  "A M Estate Agent": "07738207869",
  "SHETH PROPERTIES": "09967999901",
  "SilverKey Marketing Services LLP": "09820094078",
  "Kotecha & Company": "02222612059",
  "Tirthankar Investments": "09833959607",
  "Raj Property And Estate Consultant": "09969179918",
  "Sudesh Kapoor Real Estate Consultancy": "09819056666",
  "Walk 2 Dreams Home LLP": "09920048811",
  "Dhf Realtors": "02222151965",
  "Mumbai Estate Brokers": "09769698383",
  "Primon Properties": "09821157122",
  "J.G.A. Shah Share Brokers Private Limited": "02267522025",
  "BC Corp. - (HB Realty)": "02223514427",
  "Colaba Real Estate": "09167555222",
  "Easy Enterprises Estate Consultants": "02223803750",
  "Agarwal Real Estate Consultant": "02222092303",
  "Chris Realestate": "08169157378",
  "De Villa Estate": "07666699333",
  "Sweet Homez Realty Infraheights Pvt Ltd.": "09167907786",
  "Mr. Rahul Shah": "09004771112",
  "High Street Realtors": "09820043057",
  "Stallion Associates": "09198198664",
  "Cosmos Properties & Estate Consultants": "09619360604",
  "thepropcart.com": "08268444333",
  "Vijay Estate Agency": "09820157062",
  "SAISH PROPERTIES": "09892134050",
  "HDFC ERGO Insurance Agent: Manohardevi G Dagliya": "09702560704",
  "HDFC ERGO Insurance Agent: Viraaj B Makwana": "08424981954",
  "Zed Realty": "09833822822",
  "RODIA CONSULTANCY SERVICES": "09820027000",
  "HDFC ERGO Insurance Agent: Dharmit Kirti Shah": "08291261743",
  "Key Realty": "09819356108",
  "MD Real Estate": "09967214287",
  "F. E. Dinshaw Estate": "02222624662",
  "Durga Realtors": "09323002424",
  "Able Properties Limited": "02223519101",
  "Excellence REAFS Private Limited (Head office)": "08591645514",
  "Praxis Insurance Broking Solutions Pvt Ltd": "02223454747",
  "Aditi Properties": "09819866142",
  "Distress Deals": "09184250909",
  "Sharmila Auto": "09769994088",
  "Shri Laxmi Properties": "09324636479",
  "Dwelling Solution": "02223511173",
  "HDFC ERGO Insurance Agent: Nitesh Tejraj Jain": "08879120657",
  "SRI PROPERTY CONSULTANCY": "09869002111",
  "HDFC ERGO Insurance Agent: Pinal Mehul Upadhyay": "08424083979",
  "Nagarwalla Estates Pvt. Ltd.": "02223673265",
  "Real Estates": "09833151550",
  "Nice Insurance Landmark": "02222428883",
  "Ghanshyam Fatnani": "09821133492",
  "ACE LifeSpaces": "08879628969",
  "1BHK2BHK.com": "09022524201",
  "Shriram Finance Limited": "09513400340",
  "Reliable Enterprises": "02223441979",
  "NIRVANA_MUMBAI": "09820308217",
  "Propvantage Proptech Pvt Ltd.": "09769775716",
  "Finman Capital Services": "02223817700",
  "Electra Estate Pvt. Ltd": "02243518888",
  "Muthoot FinCorp Gold Loan": "09289059369",
  "Elpro International Ltd": "02222023075",
  "One Marina": "08097947349",
  "Avenue properties": "09768280373",
  "Vailankanni Estate Consultant": "09820334489",
  "Online Tax Accounting Shugam GST Suvidha Kendra MSME Reg.": "07841028148",
  "Aditya Estate Agent": "09004683121",
  "Mahesh S. Rohra": "09820068401",
  "LANDMARK REALTY PVT LTD": "07302564492",
  "Prem Estate Agents": "09820050681",
  "Jash Realtors": "09320665355",
  "Mumbai real estate": "09220560344",
  "Lucky Express Enterprises Estate Agent": "02222046785",
  "Just Home": "02241235814",
  "Shelter Trading & Consultancy Services Pvt. Ltd": "02266316764",
  "GOLDEN TRIANGLE PROPERTY": "02222670137",
  "Nexxus Realty": "09820947687",
  "Dilip Est Agents": "02222025622",
  "Primon Properties And Ests": "09821157122",
  "Pradip Real Estate": "08169165303",
  "Nishikant developers": "09323226898",
  "Solankies Corporates Solution Pvt.Ltd": "09702387775",
  "Surya Assocites": "09223336998",
  "M H CASA Property Consultants": "09324951333",
  "Forex International": "02222089495",
  "Sterling Properties": "09821146058",
  "Lucky Builders & Developer": "02223730076",
  "Telesto Realty Pvt. Ltd.": "02232254662",
  "Dubai Property": "09892510786",
  "Mohamed Rafiq Enterprises": "02223081733",
  "Panorama Realty": "02240025253",
  "Grade One Properties": "09819458933",
  "Square Yards, Kn Realty": "18002083344",
  "Real Estate": "08767816259",
  "A-star Real Estate": "02223731041",
  "The Biggest Real Estate Event India": "09757013229",
  "Babubhai Estate Agents": "09619949736",
  "Al-Aziz Estate": "02265666600",
  "Dream Property Consultants": "02223819290",
  "Prime Property Managers": "02222836291",
  "Shree Ganesh Est Agent": "09892830886",
  "Hayat Real Estate & Enterprises": "09820091821",
  "Oak Hills Realtors": "09004305645",
  "Brij Estate Agency": "09820777797",
  "Brijreqlty": "09869036657",
  "Shreenath Insurance Services": "09892073794",
  "SAP Syndicate Finance Mumbai": "09769316720"
}